LICENSE.txt
MANIFEST.in
README.rst
setup.cfg
setup.py
ezhost/BigDataArchi.py
ezhost/ServerAbstract.py
ezhost/ServerBase.py
ezhost/ServerCommand.py
ezhost/ServerCommon.py
ezhost/ServerDjango.py
ezhost/ServerDjangoUwsgi.py
ezhost/ServerLamp.py
ezhost/ServerLists.py
ezhost/ServerLnmp.py
ezhost/ServerLnmpWordpress.py
ezhost/__init__.py
ezhost/__main__.py
ezhost/main.py
ezhost.egg-info/PKG-INFO
ezhost.egg-info/SOURCES.txt
ezhost.egg-info/dependency_links.txt
ezhost.egg-info/entry_points.txt
ezhost.egg-info/requires.txt
ezhost.egg-info/top_level.txt
ezhost/config/__init__.py
ezhost/config/apache_conf_string.py
ezhost/config/bigdata_conf_string.py
ezhost/config/django_conf_string.py
ezhost/config/nginx_conf_string.py
ezhost/config/php_conf_string.py
tests/__init__.py
tests/test_server.py