Metadata-Version: 1.1
Name: ezhost
Version: 1.5.2
Summary: Let server install became simple and easy.
Home-page: https://github.com/zhexiao/ezhost.git
Author: Zhe Xiao
Author-email: zhexiao@163.com
License: MIT
Keywords: server install
Platform: UNKNOWN
Classifier: Development Status :: 5 - Production/Stable
Classifier: Intended Audience :: Developers
Classifier: Topic :: Software Development :: Build Tools
Classifier: License :: OSI Approved :: MIT License
Classifier: Programming Language :: Python :: 3
Classifier: Programming Language :: Python :: 3.3
Classifier: Programming Language :: Python :: 3.4
Classifier: Programming Language :: Python :: 3.5
Classifier: Programming Language :: Python :: 3.6
